djangopost/__init__.py
djangopost/admin.py
djangopost/apps.py
djangopost/tests.py
djangopost/urls.py
djangopost/contexts/CategoryContext.py
djangopost/contexts/__init__.py
djangopost/contexts/__pycache__/CategoryContext.cpython-38.pyc
djangopost/contexts/__pycache__/__init__.cpython-38.pyc
djangopost/extra/ImageUploadDestination.py
djangopost/extra/__init__.py
djangopost/forms/ArticleForm.py
djangopost/forms/CategoryForm.py
djangopost/forms/__init__.py
djangopost/forms/__pycache__/ArticleForm.cpython-38.pyc
djangopost/forms/__pycache__/CategoryForm.cpython-38.pyc
djangopost/forms/__pycache__/__init__.cpython-38.pyc
djangopost/managers/ArticleModelManager.py
djangopost/managers/CategoryModelManager.py
djangopost/managers/__init__.py
djangopost/managers/__pycache__/ArticleModelManager.cpython-38.pyc
djangopost/managers/__pycache__/CategoryModelManager.cpython-38.pyc
djangopost/managers/__pycache__/__init__.cpython-38.pyc
djangopost/migrations/0001_initial.py
djangopost/migrations/__init__.py
djangopost/migrations/__pycache__/0001_initial.cpython-38.pyc
djangopost/migrations/__pycache__/__init__.cpython-38.pyc
djangopost/modeladmins/ArticleModelAdmin.py
djangopost/modeladmins/CategoryModelAdmin.py
djangopost/modeladmins/__init__.py
djangopost/modeladmins/__pycache__/ArticleModelAdmin.cpython-38.pyc
djangopost/modeladmins/__pycache__/CategoryModelAdmin.cpython-38.pyc
djangopost/modeladmins/__pycache__/__init__.cpython-38.pyc
djangopost/models/ArticleModel.py
djangopost/models/CategoryModel.py
djangopost/models/__init__.py
djangopost/models/__pycache__/ArticleModel.cpython-38.pyc
djangopost/models/__pycache__/CategoryModel.cpython-38.pyc
djangopost/models/__pycache__/__init__.cpython-38.pyc
djangopost/querysets/ArticleModelQuerySet.py
djangopost/querysets/CategoryModelQuerySet.py
djangopost/querysets/__init__.py
djangopost/querysets/__pycache__/ArticleModelQuerySet.cpython-38.pyc
djangopost/querysets/__pycache__/CategoryModelQuerySet.cpython-38.pyc
djangopost-2.2.1.dist-info/License
djangopost-2.2.1.dist-info/METADATA
djangopost-2.2.1.dist-info/WHEEL
djangopost-2.2.1.dist-info/top_level.txt
djangopost-2.2.1.dist-info/RECORD
